{"schemaVersion":3,"exportedAt":"2026-07-11T08:11:27.386Z","appVersion":"1.0","totalRegions":14,"totalPlaces":178,"totalRestaurants":200,"totalChecklistItems":0,"totalImages":0,"affiliateIds":{},"regions":[{"id":"dublin","name":"Dublin","nameIt":"Baile Átha Cliath","capital":"Dublin","lat":53.35,"lng":-6.26,"emoji":"🏛️","colour":"ff4caf50","boundingBox":{"north":53.52,"south":53.18,"east":-5.92,"west":-6.6},"placeCount":15,"restaurantCount":15,"bestTimeToVisit":"Visit in May to September for pleasant weather and vibrant cultural events.","heroImage":{"index":0,"assetPath":"","isLocal":false,"url":"","credit":""}},{"id":"dublin_and_surroundings","name":"Dublin and the Midlands","nameIt":"Baile Átha Cliath agus an Lár-Tír","capital":"Dublin","lat":53.35,"lng":-6.26,"emoji":"🏛️","colour":"ff4caf50","boundingBox":{"north":53.8,"south":52.9,"east":-5.8,"west":-7.2},"placeCount":13,"restaurantCount":14,"bestTimeToVisit":"Visit in spring (April-May) or autumn (September-October) to avoid summer crowds while enjoying mild weather.","heroImage":{"index":0,"assetPath":"","isLocal":false,"url":"","credit":""}},{"id":"south_east","name":"Southeast","nameIt":"An Deisceart Thoir","capital":"Waterford","lat":52.25,"lng":-7.59,"emoji":"🏖️","colour":"ff2196f3","boundingBox":{"north":52.84,"south":51.63,"east":-7.21,"west":-8.47},"placeCount":11,"restaurantCount":14,"bestTimeToVisit":"Best visited May to September for coastal walks and sunny weather.","heroImage":{"index":0,"assetPath":"","isLocal":false,"url":"","credit":""}},{"id":"southeast","name":"Southeast","nameIt":"An Deisceart Thoir","capital":"Waterford","lat":52.25,"lng":-7.5,"emoji":"🏰","colour":"ff2196f3","boundingBox":{"north":52.7,"south":51.8,"east":-6.8,"west":-8.3},"placeCount":11,"restaurantCount":14,"bestTimeToVisit":"Visit May to September for warm weather and to explore the coastal towns and countryside at their best.","heroImage":{"index":0,"assetPath":"","isLocal":false,"url":"","credit":""}},{"id":"south_west","name":"Southwest","nameIt":"An Deisceart Thiar","capital":"Cork","lat":51.9,"lng":-8.71,"emoji":"🏔️","colour":"ffff9800","boundingBox":{"north":52.42,"south":51.38,"east":-8.21,"west":-10.13},"placeCount":12,"restaurantCount":14,"bestTimeToVisit":"Visit May to September for dramatic landscapes and coastal scenery.","heroImage":{"index":0,"assetPath":"","isLocal":false,"url":"","credit":""}},{"id":"southwest","name":"Southwest","nameIt":"An Iarthar Thoir","capital":"Cork","lat":51.9,"lng":-8.47,"emoji":"🍺","colour":"ffff9800","boundingBox":{"north":52.4,"south":51.4,"east":-7.8,"west":-9.9},"placeCount":14,"restaurantCount":14,"bestTimeToVisit":"Visit from late spring to early autumn (May-September) for the best weather and to enjoy coastal scenery.","heroImage":{"index":0,"assetPath":"","isLocal":false,"url":"","credit":""}},{"id":"west","name":"West","nameIt":"An Iarthar","capital":"Galway","lat":53.27,"lng":-9.05,"emoji":"⛰️","colour":"ff9c27b0","boundingBox":{"north":53.85,"south":52.69,"east":-8.45,"west":-10.3},"placeCount":14,"restaurantCount":15,"bestTimeToVisit":"Best visited May to September for hiking and exploring rugged Atlantic coastlines.","heroImage":{"index":0,"assetPath":"","isLocal":false,"url":"","credit":""}},{"id":"midlands","name":"Midlands","nameIt":"An Lár","capital":"Athlone","lat":53.43,"lng":-7.94,"emoji":"🌳","colour":"ffe91e63","boundingBox":{"north":53.85,"south":53.01,"east":-7.25,"west":-8.67},"placeCount":11,"restaurantCount":14,"bestTimeToVisit":"Visit April to October for pleasant weather and exploring lakes and historic sites.","heroImage":{"index":0,"assetPath":"","isLocal":false,"url":"","credit":""}},{"id":"northwest","name":"Northwest","nameIt":"An Iarthar Thuaidh","capital":"Sligo","lat":54.27,"lng":-8.47,"emoji":"🌊","colour":"ffe91e63","boundingBox":{"north":54.8,"south":53.8,"east":-7.8,"west":-9.5},"placeCount":12,"restaurantCount":14,"bestTimeToVisit":"Visit June to September for the warmest, driest weather to explore the rugged coastline and mountains.","heroImage":{"index":0,"assetPath":"","isLocal":false,"url":"","credit":""}},{"id":"east_coast","name":"East Coast","nameIt":"Cósta an Oirthir","capital":"Drogheda","lat":53.72,"lng":-6.35,"emoji":"🌊","colour":"ff009688","boundingBox":{"north":54.01,"south":53.43,"east":-5.92,"west":-6.78},"placeCount":13,"restaurantCount":14,"bestTimeToVisit":"Best visited May to September for beach activities and coastal exploration.","heroImage":{"index":0,"assetPath":"","isLocal":false,"url":"","credit":""}},{"id":"north","name":"North","nameIt":"An Tuaisceart","capital":"Derry/Londonderry","lat":55,"lng":-7.3,"emoji":"🥾","colour":"ff009688","boundingBox":{"north":55.3,"south":54.4,"east":-6,"west":-8.2},"placeCount":14,"restaurantCount":15,"bestTimeToVisit":"Visit May to September for pleasant weather and to explore the Giant's Causeway and surrounding countryside.","heroImage":{"index":0,"assetPath":"","isLocal":false,"url":"","credit":""}},{"id":"north_east","name":"Northeast","nameIt":"An Tuaisceart Thoir","capital":"Newry","lat":54.18,"lng":-6.34,"emoji":"🧱","colour":"ff795548","boundingBox":{"north":54.45,"south":53.91,"east":-5.85,"west":-6.83},"placeCount":13,"restaurantCount":15,"bestTimeToVisit":"Visit May to September for exploring ancient sites and the Mourne Mountains.","heroImage":{"index":0,"assetPath":"","isLocal":false,"url":"","credit":""}},{"id":"north_west","name":"Northwest","nameIt":"An Tuaisceart Thiar","capital":"Derry","lat":55,"lng":-7.31,"emoji":"🏰","colour":"ff3f51b5","boundingBox":{"north":55.25,"south":54.75,"east":-6.65,"west":-8.15},"placeCount":13,"restaurantCount":14,"bestTimeToVisit":"Best visited May to September for visiting historic walled cities and dramatic coastlines.","heroImage":{"index":0,"assetPath":"","isLocal":false,"url":"","credit":""}},{"id":"midland_east","name":"Midland East","nameIt":"An Lár Oirthir","capital":"Mullingar","lat":53.52,"lng":-7.35,"emoji":"🎯","colour":"ffcddc39","boundingBox":{"north":53.85,"south":53.18,"east":-6.92,"west":-7.81},"placeCount":12,"restaurantCount":14,"bestTimeToVisit":"Visit April to October for exploring heritage sites and peaceful countryside.","heroImage":{"index":0,"assetPath":"","isLocal":false,"url":"","credit":""}}]}