{
  "title": "Food & Drink",
  "subtitle": "How to eat well in South Korea — customs, dishes and where to go.",
  "sections": [
    {
      "title": "Coffee & Café Culture [카페]",
      "icon": "coffee",
      "items": [
        {
          "kind": "tip",
          "label": "Cafés are social hubs, not just for coffee",
          "text": "South Koreans spend hours in cafés studying, working, or socializing—it's normal to nurse one coffee for 3+ hours. Most cafés have free WiFi and outlets, making them de facto co-working spaces."
        },
        {
          "kind": "dish",
          "label": "Americano [아메리카노]",
          "text": "The default coffee order, usually around 3,000-5,000 won. It's stronger and cheaper than lattes, making it the everyday choice for locals."
        },
        {
          "kind": "tip",
          "label": "Convenience store coffee is surprisingly good",
          "text": "GS25, CU, and Emart24 sell decent drip coffee for 1,500-2,500 won—perfectly serviceable if you're on a budget or in a rush."
        },
        {
          "kind": "place",
          "label": "Hongdae & Gangnam for trendy cafés",
          "text": "These neighborhoods have Instagram-worthy independent cafés with specialty coffee, but expect to pay 6,000-10,000 won per drink. Tourist areas near palaces charge premiums."
        }
      ]
    },
    {
      "title": "Must-Try Dishes [필수 음식]",
      "icon": "star",
      "items": [
        {
          "kind": "dish",
          "label": "Bibimbap [비빔밥]",
          "text": "Mixed rice topped with vegetables, meat, egg, and spicy gochujang sauce—stir it all together before eating. It's healthy, filling, and available everywhere from street stalls to restaurants."
        },
        {
          "kind": "dish",
          "label": "Korean BBQ [한우구이]",
          "text": "Grill meat at your table—beef (hanwoo) is premium but pork (dwaeji) is affordable and equally satisfying. Always order side dishes (banchan) which come free and include kimchi, pickled vegetables, and more."
        },
        {
          "kind": "dish",
          "label": "Kimchi Jjigae [김치찌개]",
          "text": "Spicy kimchi stew with pork, tofu, and vegetables—deeply comforting and cheap (8,000-12,000 won). Perfect for cold days and a true taste of home cooking."
        },
        {
          "kind": "dish",
          "label": "Tteokbokki [떡볶이]",
          "text": "Chewy rice cakes in spicy red sauce with fish cakes and vegetables—a beloved street food for 4,000-6,000 won. Highly addictive and often customizable with extra toppings."
        },
        {
          "kind": "dish",
          "label": "Jjamppong [짬뽕]",
          "text": "Spicy seafood noodle soup bursting with shrimp, squid, and mussels—order with caution if you can't handle heat. Usually 12,000-15,000 won and worth every penny."
        },
        {
          "kind": "dish",
          "label": "Kalguksu [칼국수]",
          "text": "Hand-cut noodles in a savory broth with vegetables and seafood—lighter than jjamppong but equally satisfying. A comforting lunch dish around 8,000-10,000 won."
        },
        {
          "kind": "dish",
          "label": "Hotteok [호떡]",
          "text": "Sweet Korean pancake filled with brown sugar, cinnamon, and sometimes nuts—sold at street carts for 3,000-4,000 won. Best eaten warm and perfect as a snack or dessert."
        }
      ]
    },
    {
      "title": "Where to Eat [먹는 장소]",
      "icon": "restaurant",
      "items": [
        {
          "kind": "place",
          "label": "Pojangmacha [포장마차] street tents",
          "text": "Informal outdoor food stalls serving tteokbokki, hotteok, and street snacks—super cheap (3,000-8,000 won) and where locals actually eat. Most active in evenings and near subway stations."
        },
        {
          "kind": "place",
          "label": "Sikdangs [식당] for authentic meals",
          "text": "No-frills Korean restaurants with plastic chairs and laminated menus—expect honest, delicious food at fair prices (8,000-15,000 won). These are where Korean families eat, not tourists."
        },
        {
          "kind": "place",
          "label": "Department store food courts",
          "text": "Higher prices (12,000-20,000 won) but very clean and reliable; great if you're overwhelmed by options or need a quick sit-down meal without language barriers."
        },
        {
          "kind": "tip",
          "label": "Avoid restaurants in major tourist zones",
          "text": "Myeongdong, Insadong, and palace areas inflate prices by 30-50% and serve diluted versions of authentic dishes. Venture 2-3 blocks away for better value."
        },
        {
          "kind": "place",
          "label": "Night markets like Namdaemun",
          "text": "Bustling traditional markets with hundreds of food stalls—perfect for sampling multiple dishes cheaply and seeing how locals shop and eat."
        }
      ]
    },
    {
      "title": "Reading the Menu & Ordering [메뉴판 읽기]",
      "icon": "dining",
      "items": [
        {
          "kind": "rule",
          "label": "Most menus have photos—use them",
          "text": "Point at pictures or use your phone's camera translator app (Papago or Google Translate) to photograph menu text. English menus often mistranslate dish names, so photos are more reliable."
        },
        {
          "kind": "tip",
          "label": "Spice levels matter—ask before ordering",
          "text": "If you can't handle heat, explicitly ask '맵지 않게 해주세요' (maep-ji an-ke hae-ju-se-yo, 'not spicy please'). Many Korean dishes default to fiery, and there's no shame in requesting mild."
        },
        {
          "kind": "tip",
          "label": "Banchan [반찬] are free side dishes",
          "text": "Kimchi, pickled vegetables, and other sides arrive automatically—it's part of the meal, not something to order. You can ask for refills of popular ones."
        },
        {
          "kind": "rule",
          "label": "Portion sizes are generous",
          "text": "One dish often feeds 1.5-2 people, especially soups and stews. Share or expect leftovers—restaurants freely pack extras to-go (no judgment)."
        },
        {
          "kind": "tip",
          "label": "Always check prices before ordering",
          "text": "Korean restaurants rarely have menu English but prices are always in won—watch out for 'special' or premium versions costing 2-3x more. High-end hanwoo beef can easily be 50,000+ won per serving."
        }
      ]
    },
    {
      "title": "Drinks & Alcohol [음료 & 술]",
      "icon": "bar",
      "items": [
        {
          "kind": "dish",
          "label": "Soju [소주]",
          "text": "Clear, high-proof Korean spirit (16-20% ABV)—cheap, smooth, and the default drink for social occasions. Expect 2,500-5,000 won per bottle at bars; it's often paired with fried food (chimaek culture)."
        },
        {
          "kind": "dish",
          "label": "Beer [맥주] and Soju bombs [소맥]",
          "text": "Local beers like Cass and Hite are crisp and affordable (4,000-6,000 won). Mixing beer and soju ('soju bomb') is a popular drinking game—fun but dangerous for your head the next day."
        },
        {
          "kind": "dish",
          "label": "Makgeolli [막걸리]",
          "text": "Sweet, milky rice wine (6-8% ABV) traditionally served in bowls—nostalgic and less harsh than soju. Trendy makgeolli bars have emerged, but street pojangmacha versions are authentic and cheaper."
        },
        {
          "kind": "place",
          "label": "Pojangmacha for drinking culture",
          "text": "Street tent bars serve soju and beer with fried snacks (tteokbokki, hotteok, fried chicken)—this is where Koreans drink and socialize. Expect 15,000-30,000 won per person for drinks and food."
        },
        {
          "kind": "tip",
          "label": "Chimaek [치맥] is fried chicken + beer",
          "text": "A beloved pairing: crispy, spicy fried chicken (치킨) with cold beer (맥주). Restaurants and pojangmacha focus on this—it's casual, affordable (15,000-25,000 won), and authentically Korean."
        },
        {
          "kind": "rule",
          "label": "Respectful drinking customs matter",
          "text": "When older people pour drinks, accept with both hands and turn slightly away when drinking. Never pour your own drink if others are present—it's considered rude. Always pour for others first."
        }
      ]
    },
    {
      "title": "Dining Customs & Etiquette [식사 예절]",
      "icon": "dining",
      "items": [
        {
          "kind": "rule",
          "label": "Wait for the eldest person to start eating",
          "text": "In formal settings or with Korean families, wait for the oldest person to pick up their spoon before you start. This shows respect and is deeply ingrained in Korean culture."
        },
        {
          "kind": "rule",
          "label": "Use spoons for rice and soup, chopsticks for side dishes",
          "text": "Korean etiquette specifies spoons for rice (not chopsticks), chopsticks for banchan and meat. Metal utensils are traditional and standard in most restaurants."
        },
        {
          "kind": "tip",
          "label": "Slurping noodles is acceptable and even encouraged",
          "text": "Unlike some cultures, loud slurping shows you're enjoying the food. It's normal behavior in Korean restaurants."
        },
        {
          "kind": "rule",
          "label": "Never pour your own drink—pour for others instead",
          "text": "At meals and drinks, hold the bottle with both hands and offer to pour for others first. They'll reciprocate, creating a social rhythm. Pouring your own is seen as selfish."
        },
        {
          "kind": "tip",
          "label": "Tipping is not customary and not expected",
          "text": "Unlike the US, tipping in South Korea is rare and can even be insulting. Prices shown are final, and service charges are sometimes included in bills at upscale restaurants."
        },
        {
          "kind": "tip",
          "label": "Finish your rice as a sign of respect",
          "text": "Leaving rice uneaten is considered wasteful and disrespectful to the cook, especially in traditional or family settings. Always finish or ask for a small portion if you can't eat much."
        },
        {
          "kind": "rule",
          "label": "Payment etiquette: one person pays, or split evenly",
          "text": "It's common for the oldest or most senior person to pay, or everyone splits the bill exactly (no itemizing). Offering to pay individually is rare and can create awkwardness."
        }
      ]
    },
    {
      "title": "Practical Tips & Language [실용 팁]",
      "icon": "star",
      "items": [
        {
          "kind": "tip",
          "label": "Learn basic food phrases",
          "text": "Key phrases: '맛있어요!' (mat-iseo-yo, 'delicious!'), '물 주세요' (mul ju-se-yo, 'water please'), '계산서 주세요' (gye-san-seo ju-se-yo, 'bill please'). Koreans appreciate effort and are forgiving of mistakes."
        },
        {
          "kind": "tip",
          "label": "Download a translation app",
          "text": "Papago (Korean-native) or Google Translate's camera feature are lifesavers for reading menus and understanding prices. Most restaurants lack English, so these tools are essential."
        },
        {
          "kind": "tip",
          "label": "Allergen warnings: tell staff immediately",
          "text": "If you have allergies, write them down or use your phone to show them clearly. Many dishes contain hidden sesame, shellfish, or soy, so don't assume—always confirm."
        },
        {
          "kind": "tip",
          "label": "Cash is still king at street food and small restaurants",
          "text": "While cards are accepted everywhere, many pojangmacha and small sikdangs are cash-only. Keep 10,000-50,000 won notes handy."
        }
      ]
    }
  ]
}